processlib/__init__.py
processlib/activity.py
processlib/apps.py
processlib/assignment.py
processlib/flow.py
processlib/models.py
processlib/serializers.py
processlib/services.py
processlib/signals.py
processlib/tasks.py
processlib/tests.py
processlib/urls.py
processlib/views.py
processlib/migrations/0001_initial.py
processlib/migrations/__init__.py
processlib/templatetags/__init__.py
processlib/templatetags/processlib_tags.py
processlib-0.5.1.dist-info/METADATA
processlib-0.5.1.dist-info/RECORD
processlib-0.5.1.dist-info/WHEEL
processlib-0.5.1.dist-info/top_level.txt
