Metadata-Version: 2.1
Name: processlib
Version: 0.5.1
Summary: A workflow library for python
Home-page: https://github.com/RaphaelKimmig/processlib
Author: Raphael Kimmig
Author-email: raphael@ampad.de
License: UNKNOWN
Download-URL: https://github.com/RaphaelKimmig/processlib/archive/0.5.1.tar.gz
Platform: UNKNOWN
Requires-Dist: django (>=1.11)
